autocontext/__init__.py
autocontext/autocontext.py
autocontext/models.py
iolanta/__init__.py
iolanta/cli/__init__.py
iolanta/cli/pretty_print.py
iolanta/context.py
iolanta/conversions.py
iolanta/convert_dollar_signs.py
iolanta/facet.py
iolanta/facets/__init__.py
iolanta/facets/base.py
iolanta/facets/by_environment.py
iolanta/facets/by_instance.py
iolanta/facets/by_literal_datatype.py
iolanta/facets/by_type.py
iolanta/facets/errors.py
iolanta/facets/for_literal.py
iolanta/facets/sparql/find_facet_by_instance_types.sparql
iolanta/facets/sparql/find_facet_for_literal.sparql
iolanta/loaders/__init__.py
iolanta/loaders/base.py
iolanta/loaders/local_file.py
iolanta/loaders/named.py
iolanta/loaders/scheme_choice.py
iolanta/models.py
iolanta/namespaces.py
iolanta/parsers/__init__.py
iolanta/parsers/base.py
iolanta/parsers/errors.py
iolanta/parsers/json.py
iolanta/parsers/markdown.py
iolanta/parsers/yaml.py
iolanta/reformat_blank_nodes.py
iolanta/shortcuts.py
ldflex/__init__.py
ldflex/ldflex.py
octadocs/__init__.py
octadocs/cli/__init__.py
octadocs/cli/context.py
octadocs/cli/formatters/__init__.py
octadocs/cli/formatters/choose.py
octadocs/cli/formatters/csv.py
octadocs/cli/formatters/json.py
octadocs/cli/formatters/node_to_qname.py
octadocs/cli/formatters/pretty.py
octadocs/cli/main.py
octadocs/cli/show.py
octadocs/cli/sparql.py
octadocs/cli/update.py
octadocs/conversions.py
octadocs/data/foaf/foaf.json
octadocs/data/foaf/named-context.json
octadocs/data/iolanta/named-context.json
octadocs/data/octa/named-context.json
octadocs/data/owl/named-context.json
octadocs/data/owl/owl.json
octadocs/data/rdf/named-context.json
octadocs/data/rdf/rdf.json
octadocs/data/rdfs/named-context.json
octadocs/data/rdfs/rdfs.json
octadocs/data/skos/named-context.json
octadocs/data/skos/skos.json
octadocs/default_context.py
octadocs/describe_documentation_page.py
octadocs/environment.py
octadocs/facets/__init__.py
octadocs/facets/bool_literal.py
octadocs/facets/date_literal.py
octadocs-0.2.32.dist-info/entry_points.txt
octadocs-0.2.32.dist-info/LICENSE
octadocs-0.2.32.dist-info/WHEEL
octadocs-0.2.32.dist-info/METADATA
octadocs-0.2.32.dist-info/RECORD
